aih/__init__.py
aih/aih.py
aih_diendn-0.1.1.dist-info/METADATA
aih_diendn-0.1.1.dist-info/WHEEL
aih_diendn-0.1.1.dist-info/top_level.txt
aih_diendn-0.1.1.dist-info/RECORD
